Workbook

Sheet Comms
D4: WSP/Brl | E4: Increase from 05.03.12 | F4: WSP/Brl | G4: 36 | H4: 36 | I4: 36 | J4: 36 | K4: 36
C5: ABV % | D5: Price from 28.03.11 | F5: Price from 05.03.12 | G5: 9 | H5: 10 | I5: 11 | J5: 18 | K5: 22
D7: 36G | E7: £/brl | F7: 36G | G7: 9G | H7: 10G | I7: 11G | J7: 18G | K7: 22G
B10: Owner | C10: CATEGORY | D10: BRAND | E10: ABV | F10: WSP 28th March 2011 | G10: =E4 -> Increase from 05.03.12 | H10: WSP 5th March 2012 | I10: 50l / 11G Container Price | J10: Small Container Charge
B11: C&C | C11: Standard Lager | D11: Tennent's Lager | E11: 0.04 | F11: 449.233 | G11: 9.9818906 | H11: =G11+F11 -> 459.21489 | I11: =(H11/163.65924)*50 -> 140.29605 | J11: 0.7
B12: CT | C12: Standard Lager | D12: Carlsberg | E12: 0.038 | F12: 442.59 | G12: 18.99 | H12: =G12+F12 -> 461.58 | I12: =(H12/I$4)*I$5 -> 141.03833 | J12: 0.9
B13: Heineken | C13: Standard Lager | D13: Fosters | E13: 0.04 | F13: 446.963 | G13: 19.79 | H13: =G13+F13 -> 466.753 | I13: =(H13/I$4)*I$5 -> 142.61897 | J13: 0.9
B14: Coors | C14: Standard Lager | D14: Carling | E14: 0.04 | F14: 459.6 | G14: 19.99 | H14: =G14+F14 -> 479.59 | I14: =(H14/I$4)*I$5 -> 146.54139 | J14: 1.5
D17: BRAND | E17: ABV | F17: WSP 28th March 2011 | G17: =G10 -> Increase from 05.03.12 | H17: WSP 5th March 2012 | I17: Solus Drive Brands Discount
D18: Tennent's Lager | E18: 0.04 | F18: 449.233 | G18: 9.9818906 | H18: =G18+F18 -> 459.21489 | I18: =-G18 -> -9.9818906
D19: =#REF! -> #REF! | E19: =#REF! -> #REF! | F19: =#REF! -> #REF! | G19: =#REF! -> #REF! | H19: =#REF! -> #REF! | I19: =-G19 -> #REF!
D20: =#REF! -> #REF! | E20: =#REF! -> #REF! | F20: =#REF! -> #REF! | G20: =#REF! -> #REF! | H20: =#REF! -> #REF! | I20: =-G20 -> #REF!

Sheet BDM Copy
C2: TENNENTS SCOTLAND - FB TAVERNS WSP MARCH 2026 Draught Products | I2: Pubname | K2: Date
B4: Sku Code | C4: Brand | D4: ABV % | E4: WSP/Brl | F4: FB Taverns Total | G4: New Net Price | H4: Net Price | I4: Net Price | J4: Tennant | K4: Iona Retro
E5: 36G | F5: Discount | G5: Per Brl | H5: Per Keg | I5: Per Pint | J5: Off invoice
A7: Standard Lager | B7: 90425 | C7: Tennents Lager | D7: 0.04 | E7: 641.62 | F7: 314.33 | G7: =E7-F7 -> 327.29 | H7: =((E7-J7)/36)*11 -> 196.05056 | I7: =(H7/88) -> 2.2278472 | K7: =F7-J7 -> 314.33
B8: 400889 | C8: Jeffreys Lager | D8: 0.034 | E8: 538.39 | F8: 302.97 | G8: =E8-F8 -> 235.42 | H8: =((E8-J8)/36)*11 -> 164.50806 | I8: =(H8/88) -> 1.8694097 | K8: =F8-J8 -> 302.97
B9: T00045238 | C9: Carlsberg Pilsner | D9: 0.034 | E9: 796.51 | F9: 410 | G9: =E9-F9 -> 386.51 | H9: =((E9-J9)/36)*11 -> 243.37806 | I9: =(H9/88) -> 2.7656597 | K9: =F9-J9 -> 410
A11: Premium Lager | B11: 401136 | C11: Heverlee | D11: 0.048 | E11: 788.01 | F11: 370.14 | G11: =E11-F11 -> 417.87 | H11: =((E11-J11)/36)*11 -> 240.78083 | I11: =(H11/88) -> 2.7361458 | K11: =F11-J11 -> 370.14
B12: 400557 | C12: Menabrea | D12: 0.048 | E12: 805.6 | F12: 332 | G12: =E12-F12 -> 473.6 | H12: =((E12-J12)/36)*11 -> 246.15556 | I12: =(H12/88) -> 2.7972222 | K12: =F12-J12 -> 332
B13: 401211 | C13: Tennents Bavarian Pilsner | D13: 0.046 | E13: 778.62 | F13: 350 | G13: =E13-F13 -> 428.62 | H13: =((E13-J13)/36)*11 -> 237.91167 | I13: =(H13/88) -> 2.7035417 | K13: =F13-J13 -> 350
B14: STE025 | C14: Stella Artois | D14: 0.046 | E14: 960.76 | F14: 560 | G14: =E14-F14 -> 400.76 | H14: =((E14-J14)/36)*11 -> 293.56556 | I14: =(H14/88) -> 3.3359722 | K14: =F14-J14 -> 560
B15: T00048477 | C15: Mahou | D15: 0.048 | E15: 1031.49 | F15: 530 | G15: =E15-F15 -> 501.49 | H15: =((E15-J15)/36)*11 -> 315.1775 | I15: =(H15/88) -> 3.5815625 | K15: =F15-J15 -> 530
B16: SAN002 | C16: San Miguel | D16: 0.05 | E16: 638.73 | F16: 170 | G16: =E16-F16 -> 468.73 | H16: =((E16-J16)/36)*11 -> 195.1675 | I16: =(H16/88) -> 2.2178125 | K16: =F16-J16 -> 170
B17: EST002 | C17: Estrella Damm | D17: 0.046 | E17: 1052.98 | F17: 491 | G17: =E17-F17 -> 561.98 | H17: =((E17-J17)/36)*11 -> 321.74389 | I17: =(H17/88) -> 3.6561806 | K17: =F17-J17 -> 491
E18: 659.87
B19: 401080 | C19: Drygate Pilsner | D19: 0.04 | E19: 671.19 | F19: 228.3478 | G19: =E19-F19 -> 442.8422 | H19: =((E19-J19)/36)*11 -> 205.08583 | I19: =(H19/88) -> 2.3305208 | K19: =F19-J19 -> 228.3478
A20: Craft Beers | B20: 401079 | C20: Gladeye IPA | D20: 0.055 | E20: 643.99 | F20: 187.43135 | G20: =E20-F20 -> 456.55865 | H20: =((E20-J20)/36)*11 -> 196.77472 | I20: =(H20/88) -> 2.2360764 | K20: =F20-J20 -> 187.43135
B21: DRY025 | C21: Drygate Seven Peaks | D21: 0.05 | E21: 643.99 | F21: 153.47055 | G21: =E21-F21 -> 490.51945 | H21: =((E21-J21)/36)*11 -> 196.77472 | I21: =(H21/88) -> 2.2360764 | K21: =F21-J21 -> 153.47055
B22: DIS009 | C22: Disco Forklift Truck (50L) | D22: 0.045 | E22: 686.7 | F22: 150 | G22: =E22-F22 -> 536.7 | H22: =((E22-J22)/36)*11 -> 209.825 | I22: =(H22/54) -> 3.8856481 | K22: =F22-J22 -> 150
B23: T00044490 | C23: disco forklift truck (30L) | D23: 0.045 | E23: 675.09 | G23: =E23-F23 -> 675.09 | H23: =((E23-J23)/36)*11 -> 206.2775 | I23: =(H23/54) -> 3.8199537 | K23: =F23-J23 -> 0
B24: INN008 | C24: Innis and Gunn Lager (50L) | D24: 0.046 | E24: 778.81 | F24: 310 | G24: =E24-F24 -> 468.81 | H24: =((E24-J24)/36)*11 -> 237.96972 | I24: =(H24/88) -> 2.7042014 | K24: =F24-J24 -> 310
B25: INN005 | C25: Innis and Gunn IPA (50L) | D25: 0.042 | E25: 804.94 | F25: 250 | G25: =E25-F25 -> 554.94 | H25: =((E25-J25)/36)*11 -> 245.95389 | I25: =(H25/88) -> 2.7949306 | K25: =F25-J25 -> 250
B26: JUB002 | C26: Jubel Peach (30L) | D26: 0.04 | E26: 762.18 | F26: 200 | G26: =E26-F26 -> 562.18 | H26: =((E26-J26)/36)*6.6 -> 139.733 | I26: =H26/54 -> 2.5876481 | K26: =F26-J26 -> 200
B27: JUB003 | C27: Jubel Grapefruit (30L) | D27: 0.04 | E27: 762.18 | F27: 200 | G27: =E27-F27 -> 562.18 | H27: =((E27-J27)/36)*6.6 -> 139.733 | I27: =H27/54 -> 2.5876481 | K27: =F27-J27 -> 200
B29: 400076 | C29: Caledonia Best | D29: 0.032 | E29: 469.54 | F29: 244.02 | G29: =E29-F29 -> 225.52 | H29: =((E29-J29)/36)*11 -> 143.47056 | I29: =(H29/88) -> 1.6303472 | K29: =F29-J29 -> 244.02
A30: Ales / Stout | B30: 4723 | C30: Tennents Ember 80/- | D30: 0.042 | E30: 606.46 | F30: 315.55 | G30: =E30-F30 -> 290.91 | H30: =((E30-J30)/36)*11 -> 185.30722 | I30: =(H30/88) -> 2.1057639 | K30: =F30-J30 -> 315.55
B31: 401152 | C31: Tennents Special 70/- | D31: 0.034 | E31: 475.18 | F31: 194.66 | G31: =E31-F31 -> 280.52 | H31: =((E31-J31)/36)*11 -> 145.19389 | I31: =(H31/88) -> 1.6499306 | K31: =F31-J31 -> 194.66
B32: 4790 | C32: Tennents Light 60/- | D32: 0.031 | E32: 447.12 | F32: 271.57 | G32: =E32-F32 -> 175.55 | H32: =((E32-J32)/36)*11 -> 136.62 | I32: =(H32/88) -> 1.5525 | K32: =F32-J32 -> 271.57
B33: GUI002 | C33: Guinness Keg | D33: 0.041 | E33: 779.24 | F33: 249 | G33: =E33-F33 -> 530.24 | H33: =((E33-J33)/36)*11 -> 238.10111 | I33: =(H33/88) -> 2.7056944 | K33: =F33-J33 -> 249
B34: 401254 | C34: Tennents Stout | D34: 0.04 | E34: 654.64 | F34: 245 | G34: =E34-F34 -> 409.64 | H34: =((E34-J34)/36)*11 -> 200.02889 | I34: =(H34/88) -> 2.2730556 | K34: =F34-J34 -> 245
B35: MCE005 | C35: McEwan's Export | D35: 0.045 | E35: 770.94 | F35: 327.53 | G35: =E35-F35 -> 443.41 | H35: =((E35-J35)/36)*11 -> 235.565 | I35: =(H35/88) -> 2.676875 | K35: =F35-J35 -> 327.53
B36: MCE015 | C36: McEwan's 80/- | D36: 0.042 | E36: 756.28 | F36: 319 | G36: =E36-F36 -> 437.28 | H36: =((E36-J36)/36)*11 -> 231.08556 | I36: =(H36/88) -> 2.6259722 | K36: =F36-J36 -> 319
B37: MCE008 | C37: McEwan's 70/- | D37: 0.037 | E37: 718.11 | F37: 222 | G37: =E37-F37 -> 496.11 | H37: =((E37-J37)/36)*11 -> 219.4225 | I37: =(H37/88) -> 2.4934375 | K37: =F37-J37 -> 222
B39: 401172 | C39: Magners Ice Cold | D39: 0.045 | E39: 634.61 | F39: 332.19 | G39: =E39-F39 -> 302.42 | H39: =((E39-J39)/36)*11 -> 193.90861 | I39: =(H39/88) -> 2.2035069 | K39: =F39-J39 -> 332.19
B40: 401188 | C40: Outcider 50L | D40: 0.04 | E40: 860.72 | F40: 532.76 | G40: =E40-F40 -> 327.96 | H40: =((E40-J40)/36)*11 -> 262.99778 | I40: =(H40/88) -> 2.9886111 | K40: =F40-J40 -> 532.76
A41: Ciders | B41: 401176 | C41: Blackthorn Gold | D41: 0.047 | E41: 582.68 | F41: 293.49 | G41: =E41-F41 -> 289.19 | H41: =((E41-J41)/36)*11 -> 178.04111 | I41: =(H41/88) -> 2.0231944 | K41: =F41-J41 -> 293.49
B42: 401175 | C42: Blackthorn Dry | D42: 0.05 | E42: 556.86 | F42: 293.49 | G42: =E42-F42 -> 263.37 | H42: =((E42-J42)/36)*11 -> 170.15167 | I42: =(H42/88) -> 1.9335417 | K42: =F42-J42 -> 293.49
B43: 401178 | C43: Gaymers Old English | D43: 0.045 | E43: 578.97 | F43: 284.03 | G43: =E43-F43 -> 294.94 | H43: =((E43-J43)/36)*11 -> 176.9075 | I43: =(H43/88) -> 2.0103125 | K43: =F43-J43 -> 284.03
B44: 401173 | C44: Magners Dark Fruit | D44: 0.04 | E44: 815.54 | F44: 461.65 | G44: =E44-F44 -> 353.89 | H44: =((E44-J44)/36)*11 -> 249.19278 | I44: =(H44/88) -> 2.8317361 | K44: =F44-J44 -> 461.65
B45: 401174 | C45: Orchard Pig Reveller Cider | D45: 0.045 | E45: 782.28 | F45: 406.59 | G45: =E45-F45 -> 375.69 | H45: =((E45-J45)/36)*11 -> 239.03 | I45: =(H45/88) -> 2.71625 | K45: =F45-J45 -> 406.59

Sheet Customer Copy
C2: TENNENTS SCOTLAND - FB TAVERNS WSP 2026
B4: Sku Code | C4: Brand | D4: ABV % | E4: WSP/Brl | F4: Net Price | G4: Net Price | H4: Retail Price | I4: GP % | J4: Cash Margin | K4: Tennant
E5: 36G | F5: Per Keg | G5: Per Pint | H5: Per Pint | K5: Off invoice
A7: Standard Lager | B7: 90425 | C7: Tennents Lager | D7: 0.04 | E7: 641.62 | F7: ='BDM Copy'!H7 -> 196.05056 | G7: =(F7/88) -> 2.2278472 | I7: =((H7/1.2)-G7)/(H7/1.2) -> #DIV/0! | J7: =H7-G7 -> -2.2278472 | K7: ='BDM Copy'!J7 -> 0
B8: 400889 | C8: Jeffreys Lager | D8: 0.034 | E8: 538.39 | F8: ='BDM Copy'!H8 -> 164.50806 | G8: =(F8/88) -> 1.8694097 | H8: 4 | I8: =((H8/1.2)-G8)/(H8/1.2) -> 0.43917708 | J8: =H8-G8 -> 2.1305903 | K8: ='BDM Copy'!J8 -> 0
A10: Premium Lager | B10: 400217 | C10: Heverlee | D10: 0.048 | E10: 788.01 | F10: ='BDM Copy'!H11 -> 240.78083 | G10: =(F10/88) -> 2.7361458 | I10: =((H10/1.2)-G10)/(H10/1.2) -> #DIV/0! | J10: =H10-G10 -> -2.7361458 | K10: ='BDM Copy'!J11 -> 0
B11: 400557/400751 | C11: Menabrea | D11: 0.048 | E11: 805.6 | F11: ='BDM Copy'!H12 -> 246.15556 | G11: =(F11/88) -> 2.7972222 | I11: =((H11/1.2)-G11)/(H11/1.2) -> #DIV/0! | J11: =H11-G11 -> -2.7972222 | K11: ='BDM Copy'!J12 -> 0
B12: STE025 | C12: Stella Artois | D12: 0.046 | E12: 960.76 | F12: ='BDM Copy'!H14 -> 293.56556 | G12: =(F12/80) -> 3.6695694 | I12: =((H12/1.2)-G12)/(H12/1.2) -> #DIV/0! | J12: =H12-G12 -> -3.6695694 | K12: ='BDM Copy'!J14 -> 0
B13: T00048477 | C13: Mahou | D13: 0.048 | E13: 1031.49 | F13: ='BDM Copy'!H15 -> 315.1775 | G13: =(F13/80) -> 3.9397187 | I13: =((H13/1.2)-G13)/(H13/1.2) -> #DIV/0! | J13: =H13-G13 -> -3.9397187
B14: SAN002 | C14: San Miguel | D14: 0.05 | E14: 638.73 | F14: ='BDM Copy'!H16 -> 195.1675 | G14: =(F14/80) -> 2.4395937 | I14: =((H14/1.2)-G14)/(H14/1.2) -> #DIV/0! | J14: =H14-G14 -> -2.4395937
B15: EST002 | C15: Estrella Damm | D15: 0.046 | E15: 1052.98 | F15: ='BDM Copy'!H17 -> 321.74389 | G15: =(F15/88) -> 3.6561806 | I15: =((H15/1.2)-G15)/(H15/1.2) -> #DIV/0! | J15: =H15-G15 -> -3.6561806 | K15: ='BDM Copy'!J17 -> 0
A17: Craft Beers | B17: DRY019 | C17: Drygate Pilsner | D17: 0.04 | E17: 659.87 | F17: ='BDM Copy'!H19 -> 205.08583 | G17: =(F17/88) -> 2.3305208 | I17: =((H17/1.2)-G17)/(H17/1.2) -> #DIV/0! | J17: =H17-G17 -> -2.3305208 | K17: ='BDM Copy'!J19 -> 0
B18: GLA006 | C18: Gladeye IPA | D18: 0.055 | E18: 671.19 | F18: ='BDM Copy'!H20 -> 196.77472 | G18: =(F18/88) -> 2.2360764 | I18: =((H18/1.2)-G18)/(H18/1.2) -> #DIV/0! | J18: =H18-G18 -> -2.2360764 | K18: ='BDM Copy'!J20 -> 0
B19: DRY025 | C19: Drygate Seven Peaks | D19: 0.05 | E19: 643.99 | F19: ='BDM Copy'!H21 -> 196.77472 | G19: =(F19/54) -> 3.6439763 | I19: =((H19/1.2)-G19)/(H19/1.2) -> #DIV/0! | J19: =H19-G19 -> -3.6439763 | K19: ='BDM Copy'!J21 -> 0
B20: DIS008/DIS004 | C20: Disco Forklift Truck (30L) | D20: 0.045 | E20: 686.7 | F20: ='BDM Copy'!H22 -> 209.825 | G20: =(F20/54) -> 3.8856481 | I20: =((H20/1.2)-G20)/(H20/1.2) -> #DIV/0! | J20: =H20-G20 -> -3.8856481 | K20: ='BDM Copy'!J22 -> 0
B21: INN008 | C21: Innis and Gunn Lager | D21: 0.046 | E21: 778.81 | F21: ='BDM Copy'!H24 -> 237.96972 | G21: =(F21/88) -> 2.7042014 | I21: =((H21/1.2)-G21)/(H21/1.2) -> #DIV/0! | J21: =H21-G21 -> -2.7042014 | K21: ='BDM Copy'!J24 -> 0
B22: INN005 | C22: Innis and Gunn IPA | D22: 0.042 | E22: 804.94 | F22: ='BDM Copy'!H25 -> 245.95389 | G22: =(F22/88) -> 2.7949306 | I22: =((H22/1.2)-G22)/(H22/1.2) -> #DIV/0! | J22: =H22-G22 -> -2.7949306 | K22: ='BDM Copy'!J25 -> 0
B23: JUB002 | C23: Jubel Peach (30L) | D23: 0.04 | E23: 762.18 | F23: ='BDM Copy'!H26 -> 139.733 | G23: =(F23/54) -> 2.5876481 | I23: =((H23/1.2)-G23)/(H23/1.2) -> #DIV/0! | J23: =H23-G23 -> -2.5876481 | K23: ='BDM Copy'!J26 -> 0
B24: JUB003 | C24: Jubel Grapefruit (30L) | D24: 0.04 | E24: 762.18 | F24: ='BDM Copy'!H27 -> 139.733 | G24: =(F24/54) -> 2.5876481 | I24: =((H24/1.2)-G24)/(H24/1.2) -> #DIV/0! | J24: =H24-G24 -> -2.5876481 | K24: ='BDM Copy'!J27 -> 0
A26: Ales / Stout | B26: 400076/400745 | C26: Caledonia Best | D26: 0.032 | E26: 469.54 | F26: ='BDM Copy'!H29 -> 143.47056 | G26: =(F26/88) -> 1.6303472 | H26: 4 | I26: =((H26/1.2)-G26)/(H26/1.2) -> 0.51089583 | J26: =H26-G26 -> 2.3696528 | K26: ='BDM Copy'!J29 -> 0
B27: 4723 | C27: Tennents Ember 80/- | D27: 0.042 | E27: 606.46 | F27: ='BDM Copy'!H30 -> 185.30722 | G27: =(F27/88) -> 2.1057639 | I27: =((H27/1.2)-G27)/(H27/1.2) -> #DIV/0! | J27: =H27-G27 -> -2.1057639 | K27: ='BDM Copy'!J30 -> 0
B28: 401152 | C28: Tennents Special 70/- | D28: 0.034 | E28: 475.18 | F28: ='BDM Copy'!H31 -> 145.19389 | G28: =(F28/88) -> 1.6499306 | I28: =((H28/1.2)-G28)/(H28/1.2) -> #DIV/0! | J28: =H28-G28 -> -1.6499306 | K28: ='BDM Copy'!J31 -> 0
B29: 4790 | C29: Tennents Light 60/- | D29: 0.031 | E29: 447.12 | F29: ='BDM Copy'!H32 -> 136.62 | G29: =(F29/88) -> 1.5525 | I29: =((H29/1.2)-G29)/(H29/1.2) -> #DIV/0! | J29: =H29-G29 -> -1.5525 | K29: ='BDM Copy'!J32 -> 0
B30: GUI002/GUI003 | C30: Guinness Keg | D30: 0.041 | E30: 779.24 | F30: ='BDM Copy'!H33 -> 238.10111 | G30: =(F30/88) -> 2.7056944 | I30: =((H30/1.2)-G30)/(H30/1.2) -> #DIV/0! | J30: =H30-G30 -> -2.7056944 | K30: ='BDM Copy'!J33 -> 0
B31: MCE005 | C31: McEwan's Export | D31: 0.045 | E31: 770.94 | F31: ='BDM Copy'!H35 -> 235.565 | G31: =(F31/88) -> 2.676875 | I31: =((H31/1.2)-G31)/(H31/1.2) -> #DIV/0! | J31: =H31-G31 -> -2.676875 | K31: ='BDM Copy'!J35 -> 0
B32: MCE015 | C32: McEwan's 80/- | D32: 0.042 | E32: 756.28 | F32: ='BDM Copy'!H36 -> 231.08556 | G32: =(F32/88) -> 2.6259722 | I32: =((H32/1.2)-G32)/(H32/1.2) -> #DIV/0! | J32: =H32-G32 -> -2.6259722 | K32: ='BDM Copy'!J36 -> 0
B34: 401172 | C34: Magners Ice Cold | D34: 0.045 | E34: 634.61 | F34: ='BDM Copy'!H39 -> 193.90861 | G34: =(F34/88) -> 2.2035069 | I34: =((H34/1.2)-G34)/(H34/1.2) -> #DIV/0! | J34: =H34-G34 -> -2.2035069 | K34: ='BDM Copy'!J39 -> 0
B35: 401188 | C35: Outcider 50L | D35: 0.04 | E35: 860.72 | F35: ='BDM Copy'!H40 -> 262.99778 | G35: =(F35/88) -> 2.9886111 | I35: =((H35/1.2)-G35)/(H35/1.2) -> #DIV/0! | J35: =H35-G35 -> -2.9886111 | K35: ='BDM Copy'!J40 -> 0
A36: Ciders | B36: 401176 | C36: Blackthorn Gold | D36: 0.047 | E36: 612.37 | F36: ='BDM Copy'!H41 -> 178.04111 | G36: =(F36/88) -> 2.0231944 | I36: =((H36/1.2)-G36)/(H36/1.2) -> #DIV/0! | J36: =H36-G36 -> -2.0231944 | K36: ='BDM Copy'!J41 -> 0
B37: 401175 | C37: Blackthorn Dry | D37: 0.05 | E37: 612.37 | F37: ='BDM Copy'!H42 -> 170.15167 | G37: =(F37/88) -> 1.9335417 | I37: =((H37/1.2)-G37)/(H37/1.2) -> #DIV/0! | J37: =H37-G37 -> -1.9335417 | K37: ='BDM Copy'!J42 -> 0
B38: 401178 | C38: Gaymers Old English | D38: 0.045 | E38: 578.97 | F38: ='BDM Copy'!H43 -> 176.9075 | G38: =(F38/88) -> 2.0103125 | I38: =((H38/1.2)-G38)/(H38/1.2) -> #DIV/0! | J38: =H38-G38 -> -2.0103125 | K38: ='BDM Copy'!J43 -> 0
B39: 401173 | C39: Magners Dark Fruit | D39: 0.04 | E39: 815.54 | F39: ='BDM Copy'!H44 -> 249.19278 | G39: =(F39/88) -> 2.8317361 | I39: =((H39/1.2)-G39)/(H39/1.2) -> #DIV/0! | J39: =H39-G39 -> -2.8317361 | K39: ='BDM Copy'!J44 -> 0
B40: 401174 | C40: Orchard Pig Reveller Cider | D40: 0.045 | E40: 782.28 | F40: ='BDM Copy'!H45 -> 239.03 | G40: =(F40/88) -> 2.71625 | I40: =((H40/1.2)-G40)/(H40/1.2) -> #DIV/0! | J40: =H40-G40 -> -2.71625 | K40: ='BDM Copy'!J45 -> 0
